rasa_cli_completion/__init__.py
rasa_cli_completion/rasa-complete.sh
rasa_cli_completion/rasa_complete.py
rasa_cli_completion/show_config.py
tests/__init__.py
tests/test_rasa_complete.py
rasa_cli_completion-0.1.1.dist-info/LICENSE
rasa_cli_completion-0.1.1.dist-info/METADATA
rasa_cli_completion-0.1.1.dist-info/WHEEL
rasa_cli_completion-0.1.1.dist-info/top_level.txt
rasa_cli_completion-0.1.1.dist-info/RECORD
