Metadata-Version: 2.1
Name: rasa-cli-completion
Version: 0.1.1
Summary: Bash / Zsh autocomplete script for Rasa
Home-page: UNKNOWN
Maintainer: Tobias Wochinger
Maintainer-email: tobias.wochinger@gmail.com
License: Apache 2.0
Project-URL: Bug Reports, https://github.com/wochinge/rasa-cli-completion/issues
Project-URL: Source, https://github.com/wochinge/rasa-cli-completion
Platform: UNKNOWN
Classifier: Development Status :: 4 - Beta
Classifier: Intended Audience :: Developers
Classifier: License :: OSI Approved :: Apache Software License
Classifier: Programming Language :: Python
Classifier: Programming Language :: Python :: 3.6
Classifier: Programming Language :: Python :: 3.7
Classifier: Topic :: Software Development :: Libraries
Requires-Python: >=3.6
Requires-Dist: rasa (~=1.3)
